{"version":"1.5","timestamp":1763678452,"count":49,"index":{"":{"key":"","storage_key":"","template":null,"storage_timestamp":1761779870,"children":{"01.home":1761779854,"02.a-propos":1761779854,"03.Ateliers":1761779855,"04.spectacles":1761779855,"05.gallery":1761779861,"06.partenaires":1761779870,"08.Contact":1761779870},"checksum":"f8c5593ae99f427f541bd8a21623d178"},"01.home":{"key":"home","storage_key":"01.home","template":"modular","storage_timestamp":1761779854,"markdown":{"":{"modular":1761779854}},"children":{"01._banner-accueil":1761779854,"02._about":1761779854,"03._cta1":1761779854,"04._cta3":1761779854,"05._tuiles":1761779854,"06._remerciement":1761779854},"checksum":"041b860fe9020fd2d4afcaee5ea09d3e"},"01.home\/01._banner-accueil":{"key":"home\/_banner-accueil","storage_key":"01.home\/01._banner-accueil","template":"banner-accueil","storage_timestamp":1761779854,"markdown":{"":{"banner-accueil":1761779854}},"checksum":"4c3dac1c06cbcfcd2cfa0c2bf9e3773c"},"01.home\/02._about":{"key":"home\/_about","storage_key":"01.home\/02._about","template":"about","storage_timestamp":1761779854,"markdown":{"":{"about":1761779854}},"checksum":"c739edc57663f87f8b34912d6f67e493"},"01.home\/03._cta1":{"key":"home\/_cta1","storage_key":"01.home\/03._cta1","template":"cta1","storage_timestamp":1761779854,"markdown":{"":{"cta1":1761779854}},"checksum":"652945d126fee52165a6dec6be5472ae"},"01.home\/04._cta3":{"key":"home\/_cta3","storage_key":"01.home\/04._cta3","template":"cta3","storage_timestamp":1761779854,"markdown":{"":{"cta3":1761779854}},"checksum":"35e0657c94ff5f619ad18414431b9e11"},"01.home\/05._tuiles":{"key":"home\/_tuiles","storage_key":"01.home\/05._tuiles","template":"features","storage_timestamp":1761779854,"markdown":{"":{"features":1761779854}},"checksum":"65087d41fc1b7da3232450f5e18d4215"},"01.home\/06._remerciement":{"key":"home\/_remerciement","storage_key":"01.home\/06._remerciement","template":"visions","storage_timestamp":1761779854,"markdown":{"":{"visions":1761779854}},"checksum":"f1c7718dfa0b4110bf76a2bad2a4ef80"},"02.a-propos":{"key":"a-propos","storage_key":"02.a-propos","template":"modular","storage_timestamp":1761779854,"markdown":{"":{"modular":1761779854}},"children":{"_banner":1761779854,"_cta3":1761779854,"_cta4":1761779854,"_notre-engagement":1761779854,"_visions":1761779854},"checksum":"ca09a699bde976d1a607d4330f3b80d0"},"02.a-propos\/_banner":{"key":"a-propos\/_banner","storage_key":"02.a-propos\/_banner","template":"banner","storage_timestamp":1761779854,"markdown":{"":{"banner":1761779854}},"checksum":"d7bfa3bb6dcebe52d3122143a6f6f967"},"02.a-propos\/_cta3":{"key":"a-propos\/_cta3","storage_key":"02.a-propos\/_cta3","template":"cta3","storage_timestamp":1761779854,"markdown":{"":{"cta3":1761779854}},"checksum":"47721743ccc7f758b2e2ae73f37fa6e7"},"02.a-propos\/_cta4":{"key":"a-propos\/_cta4","storage_key":"02.a-propos\/_cta4","template":"cta4","storage_timestamp":1761779854,"markdown":{"":{"cta4":1761779854}},"checksum":"69116470ff62687f01bc9508e4a71427"},"02.a-propos\/_notre-engagement":{"key":"a-propos\/_notre-engagement","storage_key":"02.a-propos\/_notre-engagement","template":"about","storage_timestamp":1761779854,"markdown":{"":{"about":1761779854}},"checksum":"1daba56c14ef23a29cc1340acc468be0"},"02.a-propos\/_visions":{"key":"a-propos\/_visions","storage_key":"02.a-propos\/_visions","template":"visions","storage_timestamp":1761779854,"markdown":{"":{"visions":1761779854}},"checksum":"e53eb271202cd1dcd645faa62a9f7c61"},"03.Ateliers":{"key":"ateliers","storage_key":"03.Ateliers","template":"blog","storage_timestamp":1761779855,"markdown":{"":{"blog":1761779855}},"children":{"01.atelier-procedes-comiques-au25":1761779854,"02.atelier-ecriture-creative-au25":1761779854,"03.atelier-exageration-au25":1761779854,"04.atelier-1-theatre-corporel":1761779854,"05.atelier-4-comedie-physique":1761779855,"06.atelier-5-theatre-corporel":1761779855,"07.atelier-3-voix-et-diction":1761779855,"08.atelier-6-creer-des-personnages":1761779855,"09.atelier-7-voix-et-diction":1761779855,"10.atelier-8-comedie-physique":1761779855,"11.atelier-2-creer-des-personnages":1761779855,"12.ecriture-hiv2025":1761779855,"13.sous-clef":1761779855,"14.creer-des-personnages-hiv25":1761779855,"15.atelier-voix-et-diction-au25":1761779855,"16.atelier-jeu-et-techniques-dart-clownesque-au25":1761779855,"17.atelier-rythmique-et-choeur-au25":1761779855,"18.atelier-exageration-2au25":1761779855},"checksum":"315e4858c729fa4276026c9452c07389"},"03.Ateliers\/01.atelier-procedes-comiques-au25":{"key":"ateliers\/atelier-procedes-comiques-au25","storage_key":"03.Ateliers\/01.atelier-procedes-comiques-au25","template":"item","storage_timestamp":1761779854,"markdown":{"":{"item":1761779854}},"checksum":"9ce99f071bc5dfc018b100609554a7fd"},"03.Ateliers\/02.atelier-ecriture-creative-au25":{"key":"ateliers\/atelier-ecriture-creative-au25","storage_key":"03.Ateliers\/02.atelier-ecriture-creative-au25","template":"item","storage_timestamp":1761779854,"markdown":{"":{"item":1761779854}},"checksum":"69c9585343c958c90ec10c35fd44f3f9"},"03.Ateliers\/03.atelier-exageration-au25":{"key":"ateliers\/atelier-exageration-au25","storage_key":"03.Ateliers\/03.atelier-exageration-au25","template":"item","storage_timestamp":1761779854,"markdown":{"":{"item":1761779854}},"checksum":"8e869fcc90306e183c79654eec9d15bc"},"03.Ateliers\/04.atelier-1-theatre-corporel":{"key":"ateliers\/atelier-1-theatre-corporel","storage_key":"03.Ateliers\/04.atelier-1-theatre-corporel","template":"item","storage_timestamp":1761779854,"markdown":{"":{"item":1761779854}},"checksum":"ef9f4be48f2a2d2fc56e78467b9a35ce"},"03.Ateliers\/05.atelier-4-comedie-physique":{"key":"ateliers\/atelier-4-comedie-physique","storage_key":"03.Ateliers\/05.atelier-4-comedie-physique","template":"item","storage_timestamp":1761779855,"markdown":{"":{"item":1761779855}},"checksum":"e542e948e9d34a2bfc39271b0842ce7a"},"03.Ateliers\/06.atelier-5-theatre-corporel":{"key":"ateliers\/atelier-5-theatre-corporel","storage_key":"03.Ateliers\/06.atelier-5-theatre-corporel","template":"item","storage_timestamp":1761779855,"markdown":{"":{"item":1761779855}},"checksum":"2b9515e14e364c6bf1b6bed5993ef74d"},"03.Ateliers\/07.atelier-3-voix-et-diction":{"key":"ateliers\/atelier-3-voix-et-diction","storage_key":"03.Ateliers\/07.atelier-3-voix-et-diction","template":"item","storage_timestamp":1761779855,"markdown":{"":{"item":1761779855}},"checksum":"ca4993a4dc261af5e4aace0166a57c25"},"03.Ateliers\/08.atelier-6-creer-des-personnages":{"key":"ateliers\/atelier-6-creer-des-personnages","storage_key":"03.Ateliers\/08.atelier-6-creer-des-personnages","template":"item","storage_timestamp":1761779855,"markdown":{"":{"item":1761779855}},"checksum":"582a23d5f44c3a4181892dcc3305902e"},"03.Ateliers\/09.atelier-7-voix-et-diction":{"key":"ateliers\/atelier-7-voix-et-diction","storage_key":"03.Ateliers\/09.atelier-7-voix-et-diction","template":"item","storage_timestamp":1761779855,"markdown":{"":{"item":1761779855}},"checksum":"07911954e9b02922e7405c9cb96dcf84"},"03.Ateliers\/10.atelier-8-comedie-physique":{"key":"ateliers\/atelier-8-comedie-physique","storage_key":"03.Ateliers\/10.atelier-8-comedie-physique","template":"item","storage_timestamp":1761779855,"markdown":{"":{"item":1761779855}},"checksum":"208808bc7a727842ddfa47ed48c89184"},"03.Ateliers\/11.atelier-2-creer-des-personnages":{"key":"ateliers\/atelier-2-creer-des-personnages","storage_key":"03.Ateliers\/11.atelier-2-creer-des-personnages","template":"item","storage_timestamp":1761779855,"markdown":{"":{"item":1761779855}},"checksum":"477a6403e265110417ce6a4073a4092c"},"03.Ateliers\/12.ecriture-hiv2025":{"key":"ateliers\/ecriture-hiv2025","storage_key":"03.Ateliers\/12.ecriture-hiv2025","template":"item","storage_timestamp":1761779855,"markdown":{"":{"item":1761779855}},"checksum":"92c03ffdc74c59f3add9665213273fc1"},"03.Ateliers\/13.sous-clef":{"key":"ateliers\/sous-clef","storage_key":"03.Ateliers\/13.sous-clef","template":"item","storage_timestamp":1761779855,"markdown":{"":{"item":1761779855}},"checksum":"ae27f8649712069d1998a22d8264a7e0"},"03.Ateliers\/14.creer-des-personnages-hiv25":{"key":"ateliers\/creer-des-personnages-hiv25","storage_key":"03.Ateliers\/14.creer-des-personnages-hiv25","template":"item","storage_timestamp":1761779855,"markdown":{"":{"item":1761779855}},"checksum":"8ce8bd832ab47923ff92f6ee393b89f6"},"03.Ateliers\/15.atelier-voix-et-diction-au25":{"key":"ateliers\/atelier-voix-et-diction-au25","storage_key":"03.Ateliers\/15.atelier-voix-et-diction-au25","template":"item","storage_timestamp":1761779855,"markdown":{"":{"item":1761779855}},"checksum":"bdc2e32b0fe2f7bafabc060fa5a618d0"},"03.Ateliers\/16.atelier-jeu-et-techniques-dart-clownesque-au25":{"key":"ateliers\/atelier-jeu-et-techniques-dart-clownesque-au25","storage_key":"03.Ateliers\/16.atelier-jeu-et-techniques-dart-clownesque-au25","template":"item","storage_timestamp":1761779855,"markdown":{"":{"item":1761779855}},"checksum":"b7486d8b33d535d51047bc9025c4697b"},"03.Ateliers\/17.atelier-rythmique-et-choeur-au25":{"key":"ateliers\/atelier-rythmique-et-choeur-au25","storage_key":"03.Ateliers\/17.atelier-rythmique-et-choeur-au25","template":"item","storage_timestamp":1761779855,"markdown":{"":{"item":1761779855}},"checksum":"1a9ced59cf1ec8777c2323e679c20323"},"03.Ateliers\/18.atelier-exageration-2au25":{"key":"ateliers\/atelier-exageration-2au25","storage_key":"03.Ateliers\/18.atelier-exageration-2au25","template":"item","storage_timestamp":1761779855,"markdown":{"":{"item":1761779855}},"checksum":"dc23c1937a59b3c09f8e46f7e26f4bcd"},"04.spectacles":{"key":"spectacles","storage_key":"04.spectacles","template":"blog","storage_timestamp":1763677199,"markdown":{"":{"blog":1761779855}},"children":{"des-joues":1761779855,"detourner-la-page":1763677199,"dix-cordes-entremelees":1761779855,"sous-clef":1761779855},"checksum":"c7f31cac56615bf1c1c260b46b5ac7bd"},"04.spectacles\/des-joues":{"key":"spectacles\/des-joues","storage_key":"04.spectacles\/des-joues","template":"item","storage_timestamp":1761779855,"markdown":{"":{"item":1761779855}},"checksum":"dc4ca85d66cad34aa6410d17321f3ffa"},"04.spectacles\/detourner-la-page":{"key":"spectacles\/detourner-la-page","storage_key":"04.spectacles\/detourner-la-page","template":"item","storage_timestamp":1763678452,"markdown":{"":{"item":1763678452}},"checksum":"f0094a80d2d02c27621543691fb61908"},"04.spectacles\/dix-cordes-entremelees":{"key":"spectacles\/dix-cordes-entremelees","storage_key":"04.spectacles\/dix-cordes-entremelees","template":"item","storage_timestamp":1761779855,"markdown":{"":{"item":1761779855}},"checksum":"18a4c2d49f89011254900363b4478b76"},"04.spectacles\/sous-clef":{"key":"spectacles\/sous-clef","storage_key":"04.spectacles\/sous-clef","template":"item","storage_timestamp":1761779855,"markdown":{"":{"item":1761779855}},"checksum":"9f09bb54659748422628e7939dd6b8a4"},"05.gallery":{"key":"gallery","storage_key":"05.gallery","template":"gallery","storage_timestamp":1761779861,"markdown":{"":{"gallery":1761779861}},"children":{"event1":1761779859,"event2":1761779860,"event3":1761779861},"checksum":"9d1eb2b71226747d7d738e2f661c4f8a"},"05.gallery\/event1":{"key":"gallery\/event1","storage_key":"05.gallery\/event1","template":"gallery-item","storage_timestamp":1761779859,"markdown":{"":{"gallery-item":1761779859}},"checksum":"28049bd97a824f4c64df92b0f3032bdf"},"05.gallery\/event2":{"key":"gallery\/event2","storage_key":"05.gallery\/event2","template":"gallery-item","storage_timestamp":1761779860,"markdown":{"":{"gallery-item":1761779860}},"checksum":"35e1cb892bbd999c6b6402beb8ad6a82"},"05.gallery\/event3":{"key":"gallery\/event3","storage_key":"05.gallery\/event3","template":"gallery-item","storage_timestamp":1761779861,"markdown":{"":{"gallery-item":1761779861}},"checksum":"e29a75e5b09da120f3780afc76476a2e"},"06.partenaires":{"key":"partenaires","storage_key":"06.partenaires","template":"modular","storage_timestamp":1761779870,"markdown":{"":{"modular":1761779869}},"children":{"_banner":1761779869,"_partenaires":1761779869},"checksum":"bb3aca15e86d256b164cc924df6cd6e9"},"06.partenaires\/_banner":{"key":"partenaires\/_banner","storage_key":"06.partenaires\/_banner","template":"banner","storage_timestamp":1761779869,"markdown":{"":{"banner":1761779861}},"checksum":"8ed3513d4bbbb79b593f8cecd06e324e"},"06.partenaires\/_partenaires":{"key":"partenaires\/_partenaires","storage_key":"06.partenaires\/_partenaires","template":"partenaires","storage_timestamp":1761779869,"markdown":{"":{"partenaires":1761779869}},"checksum":"e48d6e4142e573e67965b03ad8aec176"},"08.Contact":{"key":"contact","storage_key":"08.Contact","template":"modular","storage_timestamp":1761779870,"markdown":{"":{"modular":1761779870}},"children":{"thank-you":1761779870,"_banner":1761779870,"_contact":1761779870},"checksum":"72564915042ce64ef49b2ac7dccc362c"},"08.Contact\/thank-you":{"key":"contact\/thank-you","storage_key":"08.Contact\/thank-you","template":"default","storage_timestamp":1761779870,"markdown":{"":{"default":1761779870}},"checksum":"9113461defedafabcca774eab050ac3c"},"08.Contact\/_banner":{"key":"contact\/_banner","storage_key":"08.Contact\/_banner","template":"banner","storage_timestamp":1761779870,"markdown":{"":{"banner":1761779870}},"checksum":"e16fee67b5f1b0617e26aa0d1ec41b4f"},"08.Contact\/_contact":{"key":"contact\/_contact","storage_key":"08.Contact\/_contact","template":"contact","storage_timestamp":1761779870,"markdown":{"":{"contact":1761779870}},"checksum":"2bac0a71f9051f81a01b69ed471bace0"}}}